optimisation_algorithms/GeneticAlgorithm.py
optimisation_algorithms/GradientDescent.py
optimisation_algorithms/HarmonySearch.py
optimisation_algorithms/__init__.py
optimisation_algorithms/benchmark_functions/__init__.py
optimisation_algorithms/benchmark_functions/bowl_shape.py
optimisation_algorithms/benchmark_functions/gradients.py
optimisation_algorithms/benchmark_functions/imports.py
optimisation_algorithms/benchmark_functions/many_local_minimums.py
optimisation_algorithms/benchmark_functions/other.py
optimisation_algorithms/benchmark_functions/tests.py
optimisation_algorithms/exceptions/FailedToConverge.py
optimisation_algorithms/exceptions/__init__.py
optimisation_algorithms-1.1.2.dist-info/LICENSE
optimisation_algorithms-1.1.2.dist-info/METADATA
optimisation_algorithms-1.1.2.dist-info/WHEEL
optimisation_algorithms-1.1.2.dist-info/top_level.txt
optimisation_algorithms-1.1.2.dist-info/RECORD
