Metadata-Version: 2.1
Name: optimisation_algorithms
Version: 1.1.2
Summary: A collection of the most commonly used Optimisation Algorithms for Data Science & Machine Learning
Home-page: https://github.com/Muradmustafayev-03/Optimisation-Algorithms
Author: Murad Mustafayev
Author-email: murad.mustafayev@ufaz.az
Project-URL: Bug Reports, https://github.com/Muradmustafayev-03/Optimisation-Algorithms/issues
Project-URL: Funding, https://donate.pypi.org
Project-URL: Source, https://github.com/Muradmustafayev-03/Optimisation-Algorithms/
Keywords: optimisation,optimization algorithms,algorithms,metaheuristic,ML
Classifier: Development Status :: 3 - Alpha
Classifier: Intended Audience :: Science/Research
Classifier: Topic :: Scientific/Engineering :: Artificial Intelligence
Classifier: License :: OSI Approved :: GNU General Public License v3 (GPLv3)
Classifier: Programming Language :: Python :: 3
Classifier: Programming Language :: Python :: 3.7
Classifier: Programming Language :: Python :: 3.8
Classifier: Programming Language :: Python :: 3.9
Classifier: Programming Language :: Python :: 3.10
Classifier: Programming Language :: Python :: 3 :: Only
Requires-Python: >=3.7, <4
License-File: LICENSE
